{
  "/(auth)/login/page": "app/(auth)/login/page.js",
  "/(dashboard)/candidate/page": "app/(dashboard)/candidate/page.js",
  "/(dashboard)/hr/applications/[id]/page": "app/(dashboard)/hr/applications/[id]/page.js",
  "/(dashboard)/hr/applications/page": "app/(dashboard)/hr/applications/page.js",
  "/(dashboard)/hr/jobs/[id]/page": "app/(dashboard)/hr/jobs/[id]/page.js",
  "/(dashboard)/hr/jobs/new/page": "app/(dashboard)/hr/jobs/new/page.js",
  "/(dashboard)/hr/jobs/page": "app/(dashboard)/hr/jobs/page.js",
  "/(dashboard)/hr/page": "app/(dashboard)/hr/page.js",
  "/(dashboard)/hr/team/page": "app/(dashboard)/hr/team/page.js",
  "/(dashboard)/super-admin/page": "app/(dashboard)/super-admin/page.js",
  "/(dashboard)/team/interview/[id]/page": "app/(dashboard)/team/interview/[id]/page.js",
  "/(dashboard)/team/page": "app/(dashboard)/team/page.js",
  "/(marketplace)/jobs/[slug]/page": "app/(marketplace)/jobs/[slug]/page.js",
  "/(marketplace)/jobs/page": "app/(marketplace)/jobs/page.js",
  "/_global-error/page": "app/_global-error/page.js",
  "/_not-found/page": "app/_not-found/page.js",
  "/api/applications/[id]/assign/route": "app/api/applications/[id]/assign/route.js",
  "/api/applications/[id]/route": "app/api/applications/[id]/route.js",
  "/api/applications/route": "app/api/applications/route.js",
  "/api/auth/[...nextauth]/route": "app/api/auth/[...nextauth]/route.js",
  "/api/auth/magic-link/route": "app/api/auth/magic-link/route.js",
  "/api/auth/verify-magic-link/route": "app/api/auth/verify-magic-link/route.js",
  "/api/internal/process-ai/route": "app/api/internal/process-ai/route.js",
  "/api/interviews/[id]/feedback/route": "app/api/interviews/[id]/feedback/route.js",
  "/api/jobs/[id]/publish/route": "app/api/jobs/[id]/publish/route.js",
  "/api/jobs/[id]/route": "app/api/jobs/[id]/route.js",
  "/api/jobs/route": "app/api/jobs/route.js",
  "/api/tenants/route": "app/api/tenants/route.js",
  "/api/users/route": "app/api/users/route.js",
  "/dashboard/page": "app/dashboard/page.js",
  "/favicon.ico/route": "app/favicon.ico/route.js",
  "/page": "app/page.js",
  "/unauthorized/page": "app/unauthorized/page.js"
}